scrapy_sql/__init__.py
scrapy_sql/_defaults.py
scrapy_sql/adapters.py
scrapy_sql/commands/__init__.py
scrapy_sql/commands/cmdline.py
scrapy_sql/exporters.py
scrapy_sql/feedexport.py
scrapy_sql/session.py
scrapy_sql/stmts.py
scrapy_sql/subquery_item.py
scrapy_sql/utils.py
scrapy_sql-1.0.0.dist-info/LICENSE
scrapy_sql-1.0.0.dist-info/METADATA
scrapy_sql-1.0.0.dist-info/WHEEL
scrapy_sql-1.0.0.dist-info/RECORD
