Metadata-Version: 2.1
Name: scrapy-sql
Version: 1.0.0
Summary: Combine SQLAlchemy with Scrapy
License: MIT
Author: Nicholas Mischke
Requires-Python: >=3.10,<4.0
Classifier: License :: OSI Approved :: MIT License
Classifier: Programming Language :: Python :: 3
Classifier: Programming Language :: Python :: 3.10
Classifier: Programming Language :: Python :: 3.11
Requires-Dist: descriptors (>=0.1.0,<0.2.0)
Requires-Dist: django (>=4.2.1,<5.0.0)
Requires-Dist: pytest (>=7.3.1,<8.0.0)
Requires-Dist: scrapy (>=2.9.0,<3.0.0)
Requires-Dist: sqlalchemy (>=2.0.13,<3.0.0)
